rust_accel/__init__.py
rust_accel/rust_accel.cpython-311-darwin.so
rust_accel-0.1.5.dist-info/METADATA
rust_accel-0.1.5.dist-info/WHEEL
rust_accel-0.1.5.dist-info/licenses/LICENSE
rust_accel-0.1.5.dist-info/RECORD
