Metadata-Version: 2.4
Name: rust_accel
Version: 0.1.5
Requires-Dist: numpy>=1.23
License-File: LICENSE
Summary: Safe, fast Rust kernels exposed to Python via PyO3
Home-Page: https://github.com/0rlych1kk4/rust_accel
Author-email: Orlando Trajano <orlychikka@gmail.com>
License: MIT
Requires-Python: >=3.11
